{
  "aliases": [
    "Neophyte"
  ],
  "authors": [
    "John Romita Jr.",
    "John Romita, Jr.",
    "Scott Lobdell"
  ],
  "description": "Neophyte (Simon Hall) is a fictional mutant super villain in the Marvel Comics universe and a member of the Acolytes.",
  "images": {
    "background": null,
    "thumbnail": "https://upload.wikimedia.org/wikipedia/en/c/c0/XMEN_Neophyte.jpg"
  },
  "mainColor": null,
  "name": "Neophyte",
  "partners": [
  ],
  "powers": [
    "Appear on the other side"
  ],
  "ranking": {
    "comicCount": 0,
    "eventCount": 0,
    "pageviewCount": 206,
    "serieCount": 0,
    "storyCount": 0
  },
  "secretIdentities": [
    "Simon Hall"
  ],
  "species": [
    "Mutant"
  ],
  "superName": "Neophyte",
  "teams": [
    "Acolytes"
  ],
  "urls": {
    "marvel": null,
    "wikipedia": "https://en.wikipedia.org/wiki/Neophyte_(comics)"
  }
}