{
  "aliases": [
    "Tricephalous"
  ],
  "authors": [
    "Jack Kirby",
    "Stan Lee"
  ],
  "description": "Tricephalous is the name of a three-headed monster in Marvel Comics.",
  "images": {
    "background": null,
    "thumbnail": "https://upload.wikimedia.org/wikipedia/en/thumb/0/08/Tricephalous.jpg/249px-Tricephalous.jpg"
  },
  "mainColor": null,
  "name": "Tricephalous",
  "partners": [
  ],
  "powers": [
    "Firebreathing",
    "Flight",
    "Super-strength"
  ],
  "ranking": {
    "comicCount": 0,
    "eventCount": 0,
    "pageviewCount": 135,
    "serieCount": 0,
    "storyCount": 0
  },
  "secretIdentities": [
  ],
  "species": [
    "Humanity Subspecies"
  ],
  "superName": "Tricephalous",
  "teams": [
    "Deviant"
  ],
  "urls": {
    "marvel": null,
    "wikipedia": "https://en.wikipedia.org/wiki/Tricephalous_(comics)"
  }
}